haproxytop
