Metadata-Version: 1.1
Name: haproxy-top
Version: 0.2
Summary: Commandline utility for monitoring HAProxy
Home-page: https://github.com/bcicen/haproxy-top
Author: Bradley Cicenas
Author-email: bradley.cicenas@gmail.com
License: http://opensource.org/licenses/MIT
Keywords: haproxy stats cli commandline top monitoring devops
Platform: UNKNOWN
Classifier: License :: OSI Approved :: MIT License 
Classifier: Natural Language :: English
Classifier: Programming Language :: Python
Classifier: Programming Language :: Python :: 3
